{"nodes": [{"id": "route", "label": "route.ts", "file_type": "code", "source_file": "C:\\Users\\ruper\\noizu-direct\\src\\app\\api\\admin\\popup\\route.ts", "source_location": "L1"}, {"id": "route_requireadmin", "label": "requireAdmin()", "file_type": "code", "source_file": "C:\\Users\\ruper\\noizu-direct\\src\\app\\api\\admin\\popup\\route.ts", "source_location": "L5"}, {"id": "route_get", "label": "GET()", "file_type": "code", "source_file": "C:\\Users\\ruper\\noizu-direct\\src\\app\\api\\admin\\popup\\route.ts", "source_location": "L11"}, {"id": "route_post", "label": "POST()", "file_type": "code", "source_file": "C:\\Users\\ruper\\noizu-direct\\src\\app\\api\\admin\\popup\\route.ts", "source_location": "L17"}, {"id": "route_patch", "label": "PATCH()", "file_type": "code", "source_file": "C:\\Users\\ruper\\noizu-direct\\src\\app\\api\\admin\\popup\\route.ts", "source_location": "L39"}, {"id": "route_delete", "label": "DELETE()", "file_type": "code", "source_file": "C:\\Users\\ruper\\noizu-direct\\src\\app\\api\\admin\\popup\\route.ts", "source_location": "L59"}], "edges": [{"source": "route", "target": "server", "relation": "imports_from", "confidence": "EXTRACTED", "source_file": "C:\\Users\\ruper\\noizu-direct\\src\\app\\api\\admin\\popup\\route.ts", "source_location": "L1", "weight": 1.0}, {"source": "route", "target": "auth", "relation": "imports_from", "confidence": "EXTRACTED", "source_file": "C:\\Users\\ruper\\noizu-direct\\src\\app\\api\\admin\\popup\\route.ts", "source_location": "L2", "weight": 1.0}, {"source": "route", "target": "prisma", "relation": "imports_from", "confidence": "EXTRACTED", "source_file": "C:\\Users\\ruper\\noizu-direct\\src\\app\\api\\admin\\popup\\route.ts", "source_location": "L3", "weight": 1.0}, {"source": "route", "target": "route_requireadmin", "relation": "contains", "confidence": "EXTRACTED", "source_file": "C:\\Users\\ruper\\noizu-direct\\src\\app\\api\\admin\\popup\\route.ts", "source_location": "L5", "weight": 1.0}, {"source": "route", "target": "route_get", "relation": "contains", "confidence": "EXTRACTED", "source_file": "C:\\Users\\ruper\\noizu-direct\\src\\app\\api\\admin\\popup\\route.ts", "source_location": "L11", "weight": 1.0}, {"source": "route", "target": "route_post", "relation": "contains", "confidence": "EXTRACTED", "source_file": "C:\\Users\\ruper\\noizu-direct\\src\\app\\api\\admin\\popup\\route.ts", "source_location": "L17", "weight": 1.0}, {"source": "route", "target": "route_patch", "relation": "contains", "confidence": "EXTRACTED", "source_file": "C:\\Users\\ruper\\noizu-direct\\src\\app\\api\\admin\\popup\\route.ts", "source_location": "L39", "weight": 1.0}, {"source": "route", "target": "route_delete", "relation": "contains", "confidence": "EXTRACTED", "source_file": "C:\\Users\\ruper\\noizu-direct\\src\\app\\api\\admin\\popup\\route.ts", "source_location": "L59", "weight": 1.0}, {"source": "route_get", "target": "route_requireadmin", "relation": "calls", "confidence": "INFERRED", "source_file": "C:\\Users\\ruper\\noizu-direct\\src\\app\\api\\admin\\popup\\route.ts", "source_location": "L12", "weight": 0.8}, {"source": "route_post", "target": "route_requireadmin", "relation": "calls", "confidence": "INFERRED", "source_file": "C:\\Users\\ruper\\noizu-direct\\src\\app\\api\\admin\\popup\\route.ts", "source_location": "L18", "weight": 0.8}, {"source": "route_patch", "target": "route_requireadmin", "relation": "calls", "confidence": "INFERRED", "source_file": "C:\\Users\\ruper\\noizu-direct\\src\\app\\api\\admin\\popup\\route.ts", "source_location": "L40", "weight": 0.8}, {"source": "route_delete", "target": "route_requireadmin", "relation": "calls", "confidence": "INFERRED", "source_file": "C:\\Users\\ruper\\noizu-direct\\src\\app\\api\\admin\\popup\\route.ts", "source_location": "L60", "weight": 0.8}]}