{"nodes": [{"id": "escrow_processor", "label": "escrow-processor.ts", "file_type": "code", "source_file": "src\\lib\\escrow-processor.ts", "source_location": "L1"}, {"id": "escrow_processor_runescrowprocessor", "label": "runEscrowProcessor()", "file_type": "code", "source_file": "src\\lib\\escrow-processor.ts", "source_location": "L7"}, {"id": "escrow_processor_runfulfillmentreminders", "label": "runFulfillmentReminders()", "file_type": "code", "source_file": "src\\lib\\escrow-processor.ts", "source_location": "L118"}, {"id": "escrow_processor_releaseescrow", "label": "releaseEscrow()", "file_type": "code", "source_file": "src\\lib\\escrow-processor.ts", "source_location": "L172"}, {"id": "escrow_processor_refundescrow", "label": "refundEscrow()", "file_type": "code", "source_file": "src\\lib\\escrow-processor.ts", "source_location": "L202"}], "edges": [{"source": "escrow_processor", "target": "prisma", "relation": "imports_from", "confidence": "EXTRACTED", "source_file": "src\\lib\\escrow-processor.ts", "source_location": "L1", "weight": 1.0}, {"source": "escrow_processor", "target": "notifications", "relation": "imports_from", "confidence": "EXTRACTED", "source_file": "src\\lib\\escrow-processor.ts", "source_location": "L2", "weight": 1.0}, {"source": "escrow_processor", "target": "escrow_processor_runescrowprocessor", "relation": "contains", "confidence": "EXTRACTED", "source_file": "src\\lib\\escrow-processor.ts", "source_location": "L7", "weight": 1.0}, {"source": "escrow_processor", "target": "escrow_processor_runfulfillmentreminders", "relation": "contains", "confidence": "EXTRACTED", "source_file": "src\\lib\\escrow-processor.ts", "source_location": "L118", "weight": 1.0}, {"source": "escrow_processor", "target": "escrow_processor_releaseescrow", "relation": "contains", "confidence": "EXTRACTED", "source_file": "src\\lib\\escrow-processor.ts", "source_location": "L172", "weight": 1.0}, {"source": "escrow_processor", "target": "escrow_processor_refundescrow", "relation": "contains", "confidence": "EXTRACTED", "source_file": "src\\lib\\escrow-processor.ts", "source_location": "L202", "weight": 1.0}]}