{"nodes": [{"id": "commission_defaults", "label": "commission-defaults.ts", "file_type": "code", "source_file": "src\\lib\\commission-defaults.ts", "source_location": "L1"}, {"id": "commission_defaults_parsecommissiondefaults", "label": "parseCommissionDefaults()", "file_type": "code", "source_file": "src\\lib\\commission-defaults.ts", "source_location": "L38"}, {"id": "commission_defaults_clampint", "label": "clampInt()", "file_type": "code", "source_file": "src\\lib\\commission-defaults.ts", "source_location": "L54"}, {"id": "commission_defaults_sanitizetemplates", "label": "sanitizeTemplates()", "file_type": "code", "source_file": "src\\lib\\commission-defaults.ts", "source_location": "L60"}, {"id": "commission_defaults_validatetemplate", "label": "validateTemplate()", "file_type": "code", "source_file": "src\\lib\\commission-defaults.ts", "source_location": "L82"}], "edges": [{"source": "commission_defaults", "target": "commission_defaults_parsecommissiondefaults", "relation": "contains", "confidence": "EXTRACTED", "source_file": "src\\lib\\commission-defaults.ts", "source_location": "L38", "weight": 1.0}, {"source": "commission_defaults", "target": "commission_defaults_clampint", "relation": "contains", "confidence": "EXTRACTED", "source_file": "src\\lib\\commission-defaults.ts", "source_location": "L54", "weight": 1.0}, {"source": "commission_defaults", "target": "commission_defaults_sanitizetemplates", "relation": "contains", "confidence": "EXTRACTED", "source_file": "src\\lib\\commission-defaults.ts", "source_location": "L60", "weight": 1.0}, {"source": "commission_defaults", "target": "commission_defaults_validatetemplate", "relation": "contains", "confidence": "EXTRACTED", "source_file": "src\\lib\\commission-defaults.ts", "source_location": "L82", "weight": 1.0}, {"source": "commission_defaults_parsecommissiondefaults", "target": "commission_defaults_clampint", "relation": "calls", "confidence": "INFERRED", "source_file": "src\\lib\\commission-defaults.ts", "source_location": "L43", "weight": 0.8}, {"source": "commission_defaults_parsecommissiondefaults", "target": "commission_defaults_sanitizetemplates", "relation": "calls", "confidence": "INFERRED", "source_file": "src\\lib\\commission-defaults.ts", "source_location": "L47", "weight": 0.8}]}