{"nodes": [{"id": "recommendationcalculator", "label": "recommendationCalculator.ts", "file_type": "code", "source_file": "src\\lib\\recommendationCalculator.ts", "source_location": "L1"}, {"id": "recommendationcalculator_computerecommendations", "label": "computeRecommendations()", "file_type": "code", "source_file": "src\\lib\\recommendationCalculator.ts", "source_location": "L9"}], "edges": [{"source": "recommendationcalculator", "target": "prisma", "relation": "imports_from", "confidence": "EXTRACTED", "source_file": "src\\lib\\recommendationCalculator.ts", "source_location": "L1", "weight": 1.0}, {"source": "recommendationcalculator", "target": "recommendationcalculator_computerecommendations", "relation": "contains", "confidence": "EXTRACTED", "source_file": "src\\lib\\recommendationCalculator.ts", "source_location": "L9", "weight": 1.0}]}