{"nodes": [{"id": "cartdrawer", "label": "CartDrawer.tsx", "file_type": "code", "source_file": "src\\components\\ui\\CartDrawer.tsx", "source_location": "L1"}, {"id": "cartdrawer_formatprice", "label": "formatPrice()", "file_type": "code", "source_file": "src\\components\\ui\\CartDrawer.tsx", "source_location": "L7"}, {"id": "cartdrawer_onkey", "label": "onKey()", "file_type": "code", "source_file": "src\\components\\ui\\CartDrawer.tsx", "source_location": "L16"}], "edges": [{"source": "cartdrawer", "target": "react", "relation": "imports_from", "confidence": "EXTRACTED", "source_file": "src\\components\\ui\\CartDrawer.tsx", "source_location": "L2", "weight": 1.0}, {"source": "cartdrawer", "target": "link", "relation": "imports_from", "confidence": "EXTRACTED", "source_file": "src\\components\\ui\\CartDrawer.tsx", "source_location": "L3", "weight": 1.0}, {"source": "cartdrawer", "target": "lucide_react", "relation": "imports_from", "confidence": "EXTRACTED", "source_file": "src\\components\\ui\\CartDrawer.tsx", "source_location": "L4", "weight": 1.0}, {"source": "cartdrawer", "target": "cart_store", "relation": "imports_from", "confidence": "EXTRACTED", "source_file": "src\\components\\ui\\CartDrawer.tsx", "source_location": "L5", "weight": 1.0}, {"source": "cartdrawer", "target": "cartdrawer_formatprice", "relation": "contains", "confidence": "EXTRACTED", "source_file": "src\\components\\ui\\CartDrawer.tsx", "source_location": "L7", "weight": 1.0}, {"source": "cartdrawer", "target": "cartdrawer_onkey", "relation": "contains", "confidence": "EXTRACTED", "source_file": "src\\components\\ui\\CartDrawer.tsx", "source_location": "L16", "weight": 1.0}]}